LICENSE
MANIFEST.in
README.md
requirements.txt
setup.py
usbsecurity_monitor/RemoveDrive-x64.exe
usbsecurity_monitor/RemoveDrive.exe
usbsecurity_monitor/__init__.py
usbsecurity_monitor/__version__.py
usbsecurity_monitor/constants.py
usbsecurity_monitor/exceptions.py
usbsecurity_monitor/linux.py
usbsecurity_monitor/monitor.py
usbsecurity_monitor/registry.py
usbsecurity_monitor/usbsecurity-monitor.log
usbsecurity_monitor/win32.py
usbsecurity_monitor.egg-info/PKG-INFO
usbsecurity_monitor.egg-info/SOURCES.txt
usbsecurity_monitor.egg-info/dependency_links.txt
usbsecurity_monitor.egg-info/entry_points.txt
usbsecurity_monitor.egg-info/requires.txt
usbsecurity_monitor.egg-info/top_level.txt
usbsecurity_monitor.egg-info/zip-safe
usbsecurity_monitor/__pycache__/__init__.cpython-36.pyc
usbsecurity_monitor/__pycache__/constants.cpython-36.pyc
usbsecurity_monitor/__pycache__/exceptions.cpython-36.pyc
usbsecurity_monitor/__pycache__/linux.cpython-36.pyc