Metadata-Version: 2.1
Name: usbsecurity-monitor
Version: 4.1.0
Summary: usbsecurity-monitor is the program to control USB ports
Home-page: https://pypi.org/project/usbsecurity-monitor/
Author: Alexis Torres Valdes
Author-email: alexis89.dev@gmail.com
License: LGPL
Keywords: usb,security,ports,devices,monitor
Platform: Linux
Platform: Windows
Classifier: Development Status :: 3 - Alpha
Classifier: Intended Audience :: System Administrators
Classifier: License :: OSI Approved :: GNU Lesser General Public License v2 or later (LGPLv2+)
Classifier: Programming Language :: Python :: 3.6
Classifier: Programming Language :: Python :: Implementation :: CPython
Classifier: Operating System :: POSIX :: Linux
Classifier: Operating System :: Microsoft :: Windows
Classifier: Topic :: System :: Hardware :: Universal Serial Bus (USB) :: Mass Storage
Classifier: Topic :: System :: Monitoring
Requires-Python: >=3.6
